odoo/addons/ssi_payment_order_bank_cash_voucher/README.rst
odoo/addons/ssi_payment_order_bank_cash_voucher/__init__.py
odoo/addons/ssi_payment_order_bank_cash_voucher/__manifest__.py
odoo/addons/ssi_payment_order_bank_cash_voucher/models/__init__.py
odoo/addons/ssi_payment_order_bank_cash_voucher/models/bank_payment.py
odoo/addons/ssi_payment_order_bank_cash_voucher/models/cash_payment.py
odoo/addons/ssi_payment_order_bank_cash_voucher/models/payment_order.py
odoo/addons/ssi_payment_order_bank_cash_voucher/models/payment_order_type.py
odoo/addons/ssi_payment_order_bank_cash_voucher/models/payment_request.py
odoo/addons/ssi_payment_order_bank_cash_voucher/static/description/icon.png
odoo/addons/ssi_payment_order_bank_cash_voucher/views/bank_payment_views.xml
odoo/addons/ssi_payment_order_bank_cash_voucher/views/cash_payment_views.xml
odoo/addons/ssi_payment_order_bank_cash_voucher/views/payment_order_views.xml
odoo14_addon_ssi_payment_order_bank_cash_voucher-14.0.1.0.0.dist-info/METADATA
odoo14_addon_ssi_payment_order_bank_cash_voucher-14.0.1.0.0.dist-info/WHEEL
odoo14_addon_ssi_payment_order_bank_cash_voucher-14.0.1.0.0.dist-info/top_level.txt
odoo14_addon_ssi_payment_order_bank_cash_voucher-14.0.1.0.0.dist-info/RECORD
